ipywebgl/__init__.py
ipywebgl/_frontend.py
ipywebgl/_version.py
ipywebgl/arraybuffer.py
ipywebgl/glresource.py
ipywebgl/glviewer.py
ipywebgl/labextension/build_log.json
ipywebgl/labextension/package.json
ipywebgl/labextension/static/lib_index_js.115506ce89c3f4c34456.js
ipywebgl/labextension/static/lib_index_js.115506ce89c3f4c34456.js.map
ipywebgl/labextension/static/lib_plugin_js.a4fea4dfcfff14540990.js
ipywebgl/labextension/static/lib_plugin_js.a4fea4dfcfff14540990.js.map
ipywebgl/labextension/static/lib_widgets_js.069e9fd0f0d3ce29fcfb.js
ipywebgl/labextension/static/lib_widgets_js.069e9fd0f0d3ce29fcfb.js.map
ipywebgl/labextension/static/lib_widgets_js.6af426555276a36a3c0e.js
ipywebgl/labextension/static/lib_widgets_js.6af426555276a36a3c0e.js.map
ipywebgl/labextension/static/lib_widgets_js.b12eb52f9bc8e5a1e118.js
ipywebgl/labextension/static/lib_widgets_js.b12eb52f9bc8e5a1e118.js.map
ipywebgl/labextension/static/lib_widgets_js.b9b51f13c78ab86a7e2f.js
ipywebgl/labextension/static/lib_widgets_js.b9b51f13c78ab86a7e2f.js.map
ipywebgl/labextension/static/lib_widgets_js.d6f55f870651b8e2be65.js
ipywebgl/labextension/static/lib_widgets_js.d6f55f870651b8e2be65.js.map
ipywebgl/labextension/static/lib_widgets_js.faf7d4be5b9d6f575f9f.js
ipywebgl/labextension/static/lib_widgets_js.faf7d4be5b9d6f575f9f.js.map
ipywebgl/labextension/static/remoteEntry.08b8cfb9f52c83a9d957.js.map
ipywebgl/labextension/static/remoteEntry.5ed58a5ebd60c3c18109.js.map
ipywebgl/labextension/static/remoteEntry.868c855cf96d86fc63d4.js.map
ipywebgl/labextension/static/remoteEntry.b34735ebdc60dcbc1efa.js.map
ipywebgl/labextension/static/remoteEntry.c556a7d692943695553f.js
ipywebgl/labextension/static/remoteEntry.c556a7d692943695553f.js.map
ipywebgl/labextension/static/remoteEntry.fe80b5fdc3dfba3154fd.js.map
ipywebgl/labextension/static/style.js
ipywebgl/nbextension/extension.js
ipywebgl/nbextension/index.js
ipywebgl/nbextension/index.js.map
ipywebgl-0.4.0.dist-info/METADATA
ipywebgl-0.4.0.dist-info/WHEEL
ipywebgl-0.4.0.dist-info/licenses/LICENSE.txt
ipywebgl-0.4.0.dist-info/RECORD
