Metadata-Version: 2.1
Name: ipywebgl
Version: 0.4.0
Summary: WebGL2 jupyter widget
Project-URL: Homepage, https://github.com/JeromeEippers/ipywebgl
Project-URL: Documentation, https://ipywebgl.readthedocs.io/en/latest/index.html
Author-email: Jerome Eippers <jerome@eippers.be>
License: Copyright (c) 2023 Jerome Eippers
License-File: LICENSE.txt
Keywords: IPython,Jupyter,Widgets
Classifier: Framework :: Jupyter
Classifier: Intended Audience :: Developers
Classifier: Intended Audience :: Science/Research
Classifier: License :: OSI Approved :: BSD License
Classifier: Programming Language :: Python
Classifier: Programming Language :: Python :: 3
Classifier: Programming Language :: Python :: 3.7
Classifier: Programming Language :: Python :: 3.8
Classifier: Programming Language :: Python :: 3.9
Classifier: Programming Language :: Python :: 3.10
Requires-Python: >=3.7
Requires-Dist: ipywidgets>=7.0.0
Requires-Dist: numpy
Provides-Extra: docs
Requires-Dist: jupyter-sphinx; extra == 'docs'
Requires-Dist: nbsphinx; extra == 'docs'
Requires-Dist: nbsphinx-link; extra == 'docs'
Requires-Dist: pypandoc; extra == 'docs'
Requires-Dist: pytest-check-links; extra == 'docs'
Requires-Dist: recommonmark; extra == 'docs'
Requires-Dist: sphinx-rtd-theme; extra == 'docs'
Requires-Dist: sphinx>=1.5; extra == 'docs'
Provides-Extra: examples
